hn/__init__.py
hn/api.py
hn/endpoints.py
hn/models.py
hn/tags.py
hn/utils.py
python_hn-0.0.4.dist-info/licenses/LICENSE
python_hn-0.0.4.dist-info/METADATA
python_hn-0.0.4.dist-info/WHEEL
python_hn-0.0.4.dist-info/top_level.txt
python_hn-0.0.4.dist-info/RECORD
