Metadata-Version: 2.4
Name: python-hn
Version: 0.0.4
Summary: Add your description here
Requires-Python: >=3.09
License-File: LICENSE
Requires-Dist: requests>=2.20
Dynamic: license-file
